Workbook

Sheet Assumptions
B1: P&L
C2: Quantity | D2: Measure | E2: Link
B3: Initial Investment
B4: We will purchase 350 bikes | C4: 350 | D4: Units
B5: Average price of a second-use bike | C5: 300 | D5: Euros | E5: https://www.decathlon.fr/p/velo-vtt-randonnee-st-120-noir-bleu-27-5/_/R-p-305496?mc=8640691&c=gris_orange | I5: 25.5 | K5: =I5-I6 -> 19.5
B6: Sales | I6: =6 -> 6
B7: 80% of bikes will be occupied | C7: =C4*0.8 -> 280 | D7: Units
B8: Monthly subscription | C8: 15.5 | D8: Euros | E8: https://swapfiets.fr/ | L8: 2970
B9: Fee for new customers | C9: 10 | D9: Euros
B10: Costs of Goods Sold
B11: 5% of bikes in use will need maintenance | C11: =C7*0.05 -> 14 | D11: Units
B12: Average price for general maintenance | C12: 6 | D12: Euros | M12: =L8/K5 -> 152.30769
B13: Monthly app maintenance cost | C13: 200 | D13: Euros
B14: Wage for 1 part-time mechanic per month | C14: 570 | D14: Euros | E14: https://www.playroll.com/minimum-wage/france#:~:text=compliance%20for%20you.-,What%20Is%20the%20Minimum%20Wage%20in%20France%3F,monthly%20salary%20of%20%E2%82%AC1%2C801.80. | M14: =M12*15.5 -> 2360.7692
B15: Operating Costs
B16: Rent of a store per month | C16: 1200 | D16: Euros | E16: https://www.bureauxlocaux.com/annonce/local-commercial-rennes-centre--5439-1594359
B17: Marketing & Advertising costs per month | C17: 500 | D17: Euros
B18: Wage for 1 part-time administrative person | C18: 500 | D18: Euros | E18: https://www.playroll.com/minimum-wage/france#:~:text=compliance%20for%20you.-,What%20Is%20the%20Minimum%20Wage%20in%20France%3F,monthly%20salary%20of%20%E2%82%AC1%2C801.80.
B19: Tax
B20: % on income Tax | C20: 0.15 | D20: %
B22: Balance Sheet | C22: Quantity | D22: Measure | E22: Link
B23: Division of 80% -20% of Bikes
B24: We consider to utilize 80% of bikes based on another case study from Urban Cycle solutions as they achieve 67% of their feet utilization, bringing it to our case as in Rennes we see viable to achieve our target number of 80. | E24: https://www.leoconsult.org/case-studies/bike_rentals_case_study.html?utm_source=chatgpt.com
B26: Fixed Assets
B27: We are considering 80% of the bikes as FA | C27: 280 | D27: Units
B28: Keeping the average price of 300 eur per bike | C28: =C27*300 -> 84000 | D28: euros
B29: We are considering tools and machinery | C29: 1700 | D29: euros
B30: Current Assets
B31: We are considering 20% of bikes as CA | C31: 70 | D31: units
B32: Same price | C32: =C31*300 -> 21000 | D32: euros
B33: We are keeping $20k from private capital as cash | C33: 20000 | D33: euros
B34: Current Liabilities
B35: We are taking a private loan from an angel investor to operate for the first 3 months | C35: 11000 | D35: euros
B36: Long Term Liabilities
B37: We are taking a bank loan to cover some of the initial expenses we are considering 70% loan and a 30% private capital | C37: 80000 | D37: euros
B40: Cost of Capital Assumptions
B41: Cost of equity, 10 year french bond “Obligation Assimilable du Trésor” | C41: 0.0346 | E41: https://www.theglobaleconomy.com/France/business_credit_interest_rate/?utm_source=chatgpt.com
B42: Cost of debt, Loan interest asume based on average interest given by banks | C42: 0.06 | E42: https://www.banque-france.fr/en/statistics/loans/financing-entreprises-2025-01?utm_source=chatgpt.com
B43: Tax | C43: 0.15

Sheet P&L
B3: Profit & Loss Statement
B5: Sales | C5: Monthly | D5: Yearly
B6: Monthly Subscriptions | C6: =Assumptions!C7*Assumptions!C8 -> 4340 | D6: =C6*12 -> 52080
B7: One-time fee for new users | C7: =Assumptions!C7*Assumptions!C9 -> 2800 | D7: =C7 -> 2800
B8: Total Sales | C8: =SUM(C6:C7) -> 7140 | D8: =D6+D7 -> 54880
B9: Cost of Goods Sold (COGS)
B10: - Bike Maintenance | C10: =Assumptions!C11*Assumptions!C12 -> 84 | D10: =C10*12 -> 1008
B11: - App Maintenance | C11: =Assumptions!C13 -> 200 | D11: =C11*12 -> 2400
B12: - Operational Staff Salaries | C12: =Assumptions!C14 -> 570 | D12: =C12*12 -> 6840
B13: Total COGS | C13: =SUM(C10:C12) -> 854 | D13: =SUM(D10:D12) -> 10248
B14: Gross Profit
B15: Gross Profit | C15: =C8-C13 -> 6286 | D15: =D8-D13 -> 44632
B16: Operating Expenses
B17: - Rent | C17: =Assumptions!C16 -> 1200 | D17: =C17*12 -> 14400
B18: - Marketing | C18: =Assumptions!C17 -> 500 | D18: =C18*12 -> 6000
B19: - Administrative Wages | C19: =Assumptions!C18 -> 500 | D19: =C19*12 -> 6000
B20: Total Operating Expenses | C20: =SUM(C17:C19) -> 2200 | D20: =C20*12 -> 26400
B21: Profit Before Interest & Tax
B22: Profit Before Interest & Tax | C22: =C15-C20 -> 4086 | D22: =D15-D20 -> 18232
B23: Income Tax (15%)
B24: Income Tax | C24: =C22*Assumptions!C20 -> 612.9 | D24: =D22*Assumptions!C20 -> 2734.8
B25: Net Profit
B26: Net Profit | C26: =C22-C24 -> 3473.1 | D26: =D22-D24 -> 15497.2

Sheet BS
B3: Balance Sheet
B4: Easy Velo initial investment | D4: as of nov 2025
B6: Fixed Assets
B7: Store Furniture | C7: 2200
B8: Machinery and tools | C8: 1700
B9: Bikes | C9: 84000
B10: Net Fixed Assets | D10: =SUM(C7:C9) -> 87900
B11: Curret Assets
B12: Inventory | C12: 21000
B13: Cash | C13: 20000
B14: Total current assets | D14: =SUM(C12:C13) -> 41000
B15: Current Liabilities
B16: Private loan | C16: 11000
B17: Total current liabilites | D17: =C16 -> 11000
B19: Working capital | D19: =D14-D17 -> 30000
B21: Total assets less current liabilities | D21: =D19+D10 -> 117900
B23: Long term liablities
B24: Bank Loan | C24: 80000
B25: Net assets | D25: =D21-C24 -> 37900
B27: Financed by:
B28: Loans | C28: 11000
B29: Savings | C29: 26900
B30: Equity | D30: =C28+C29 -> 37900

Sheet Cost of Capital
B2: Cost of Capital
B3: Total Capital | C3: =BS!D30 -> 37900
B4: Weight of Debt | C4: =BS!C28/(C3) -> 0.29023747
B5: Weight of Equity | C5: =BS!C29/C3 -> 0.70976253
B6: WACC | C6: =(C5*C9)+(C4*C10)*(1-C11) -> 0.039359894
B8: Assumptions
B9: Cost of equity (Risk Free) | C9: 0.0346
B10: Cost of debt (Loan interest) | C10: 0.06
B11: Tax | C11: 0.15

Sheet Break Even
B2: Break-even point (first year)
B3: Monthly subscription price | C3: 15.5
B4: Fee for new customers | C4: 10
B5: Total price | C5: =SUM(C3:C4) -> 25.5
B7: Maintenance cost | C7: 6
B8: Total variable costs | C8: =C7 -> 6
B10: Marginal Contribution | C10: =C5-C8 -> 19.5
B12: Monthly app maintenance cost | C12: 200
B13: Wage for 1 part-time mechanic per month | C13: 570
B14: Rent of a store per month | C14: 1200
B15: Marketing & Advertising costs per month | C15: 500
B16: Wage for 1 part-time administrative person | C16: 500
B17: Fixed costs | C17: =SUM(C12:C16) -> 2970
B19: Break-even point (number of subscriptions) | C19: =C17/C10 -> 152.30769
B20: Break-even point (Price of subscriptions ) | C20: =C19*C5 -> 3883.8462
